{
    "gold": {
        "14": {
            "sell": "4560",
            "buy": "4540"
        },
        "18": {
            "sell": "5860",
            "buy": "5835"
        },
        "21": {
            "sell": "6840",
            "buy": "6810"
        },
        "24": {
            "sell": "7815",
            "buy": "7785"
        }
    },
    "goldPound": {
        "price": 54720
    },
    "goldOunce": {
        "price": "4545 $"
    },
    "currencyRates": {
        "USD": 53.4248
    },
    "lastUpdate": "2026-05-20T23:41:11.365Z"
}