{
    "gold": {
        "14": {
            "sell": "3145",
            "buy": "3135"
        },
        "18": {
            "sell": "5990",
            "buy": "5965"
        },
        "21": {
            "sell": "4720",
            "buy": "4700"
        },
        "24": {
            "sell": "7990",
            "buy": "7955"
        }
    },
    "goldPound": {
        "price": 37770
    },
    "goldOunce": {
        "price": "4721 $"
    },
    "currencyRates": {
        "USD": 52.6209717
    },
    "lastUpdate": "2026-04-24T19:30:57.237Z"
}