{
    "gold": {
        "14": {
            "sell": "2525",
            "buy": "2510"
        },
        "18": {
            "sell": "4870",
            "buy": "4840"
        },
        "21": {
            "sell": "3785",
            "buy": "3765"
        },
        "24": {
            "sell": "6490",
            "buy": "6455"
        }
    },
    "goldPound": {
        "price": 45435
    },
    "goldOunce": {
        "price": "4024 $"
    },
    "currencyRates": {
        "USD": 49.0485
    },
    "lastUpdate": "2026-07-01T13:21:21.662Z"
}