{
    "gold": {
        "14": {
            "sell": "1410",
            "buy": "1390"
        },
        "18": {
            "sell": "6000",
            "buy": "5965"
        },
        "21": {
            "sell": "7000",
            "buy": "6960"
        },
        "24": {
            "sell": "8000",
            "buy": "7955"
        }
    },
    "goldPound": {
        "price": "56000"
    },
    "goldOunce": {
        "price": "248828"
    },
    "currencyRates": {
        "GBP": 70.02124,
        "AED": 14.0966519423,
        "KWD": 167.8820788176,
        "QAR": 14.2000831254,
        "JOD": 73.0191848273,
        "BHD": 137.3154954692,
        "OMR": 134.6611983627,
        "TRY": 1.1545003332,
        "CAD": 37.75881213
    },
    "lastUpdate": "2026-04-16T21:33:23.011Z"
}