{
    "gold": {
        "14": {
            "sell": "4635",
            "buy": "4605"
        },
        "18": {
            "sell": "5955",
            "buy": "5920"
        },
        "21": {
            "sell": "6950",
            "buy": "6910"
        },
        "24": {
            "sell": "7945",
            "buy": "7895"
        }
    },
    "goldPound": {
        "price": 55600
    },
    "goldOunce": {
        "price": "4714 $"
    },
    "currencyRates": {
        "USD": 51.7646
    },
    "lastUpdate": "2026-04-21T19:40:27.848Z"
}