{
    "gold": {
        "14": {
            "sell": "4235",
            "buy": "4215"
        },
        "18": {
            "sell": "5440",
            "buy": "5415"
        },
        "21": {
            "sell": "6350",
            "buy": "6320"
        },
        "24": {
            "sell": "7255",
            "buy": "7225"
        }
    },
    "goldPound": {
        "price": 50800
    },
    "goldOunce": {
        "price": "4253 $"
    },
    "currencyRates": {
        "USD": 51.7202
    },
    "lastUpdate": "2026-06-09T22:46:42.397Z"
}